lizaliblove/__init__.py
lizaliblove/ast_graph.py
lizaliblove/fibonacci.py
lizaliblove/main.py
lizaliblove-0.0.1.dist-info/METADATA
lizaliblove-0.0.1.dist-info/WHEEL
lizaliblove-0.0.1.dist-info/top_level.txt
lizaliblove-0.0.1.dist-info/RECORD
